odoo/addons/account_invoice_download_ovh/README.rst
odoo/addons/account_invoice_download_ovh/__init__.py
odoo/addons/account_invoice_download_ovh/__manifest__.py
odoo/addons/account_invoice_download_ovh/demo/ovh_demo.xml
odoo/addons/account_invoice_download_ovh/i18n/account_invoice_download_ovh.pot
odoo/addons/account_invoice_download_ovh/models/__init__.py
odoo/addons/account_invoice_download_ovh/models/account_invoice_download_config.py
odoo/addons/account_invoice_download_ovh/static/description/icon.png
odoo/addons/account_invoice_download_ovh/views/account_invoice_download_config.xml
odoo/addons/account_invoice_download_ovh/wizard/__init__.py
odoo/addons/account_invoice_download_ovh/wizard/ovh_api_credentials.py
odoo/addons/account_invoice_download_ovh/wizard/ovh_api_credentials_view.xml
odoo12_addon_account_invoice_download_ovh-12.0.1.0.1.dist-info/METADATA
odoo12_addon_account_invoice_download_ovh-12.0.1.0.1.dist-info/WHEEL
odoo12_addon_account_invoice_download_ovh-12.0.1.0.1.dist-info/top_level.txt
odoo12_addon_account_invoice_download_ovh-12.0.1.0.1.dist-info/RECORD
